task_forest_cli/__init__.py
task_forest_cli/config.py
task_forest_cli/main.py
task_forest_cli/tasks.py
task_forest_cli/user.py
task_forest_cli/utils.py
task_forest_cli-0.2.0.dist-info/LICENSE
task_forest_cli-0.2.0.dist-info/METADATA
task_forest_cli-0.2.0.dist-info/WHEEL
task_forest_cli-0.2.0.dist-info/entry_points.txt
task_forest_cli-0.2.0.dist-info/top_level.txt
task_forest_cli-0.2.0.dist-info/RECORD
