Metadata-Version: 2.1
Name: task-forest-cli
Version: 0.2.0
Summary: Tree-based task tracking for when everything is on fire (command line version).
Home-page: https://gitlab.com/task-forest/task-forest-cli
Author: TheTwitchy
Author-email: thetwitchy@thetwitchy.com
License-File: LICENSE
Requires-Dist: click
Requires-Dist: requests
Requires-Dist: rich
Requires-Dist: pendulum
